odoo/addons/account_banking_fr_lcr/README.rst
odoo/addons/account_banking_fr_lcr/__init__.py
odoo/addons/account_banking_fr_lcr/__manifest__.py
odoo/addons/account_banking_fr_lcr/post_install.py
odoo/addons/account_banking_fr_lcr/data/account_payment_method.xml
odoo/addons/account_banking_fr_lcr/demo/lcr_demo.xml
odoo/addons/account_banking_fr_lcr/i18n/account_banking_fr_lcr.pot
odoo/addons/account_banking_fr_lcr/i18n/es.po
odoo/addons/account_banking_fr_lcr/i18n/fr.po
odoo/addons/account_banking_fr_lcr/i18n/nb_NO.po
odoo/addons/account_banking_fr_lcr/models/__init__.py
odoo/addons/account_banking_fr_lcr/models/account_move_line.py
odoo/addons/account_banking_fr_lcr/models/account_payment_method.py
odoo/addons/account_banking_fr_lcr/models/account_payment_order.py
odoo/addons/account_banking_fr_lcr/readme/CONFIGURE.md
odoo/addons/account_banking_fr_lcr/readme/CONTRIBUTORS.md
odoo/addons/account_banking_fr_lcr/readme/DESCRIPTION.md
odoo/addons/account_banking_fr_lcr/readme/USAGE.md
odoo/addons/account_banking_fr_lcr/static/description/icon.png
odoo/addons/account_banking_fr_lcr/static/description/index.html
odoo_addon_account_banking_fr_lcr-17.0.1.0.1.dist-info/METADATA
odoo_addon_account_banking_fr_lcr-17.0.1.0.1.dist-info/WHEEL
odoo_addon_account_banking_fr_lcr-17.0.1.0.1.dist-info/top_level.txt
odoo_addon_account_banking_fr_lcr-17.0.1.0.1.dist-info/RECORD
