Metadata-Version: 2.1
Name: odoo-addon-account_banking_fr_lcr
Version: 17.0.1.0.1
Requires-Python: >=3.10
Requires-Dist: odoo-addon-account_payment_order>=17.0dev,<17.1dev
Requires-Dist: odoo>=17.0a,<17.1dev
Requires-Dist: unidecode
Summary: Create French LCR CFONB files
Home-page: https://github.com/OCA/l10n-france
License: AGPL-3
Author: Akretion,Odoo Community Association (OCA)
Author-email: support@odoo-community.org
Classifier: Programming Language :: Python
Classifier: Framework :: Odoo
Classifier: Framework :: Odoo :: 17.0
Classifier: License :: OSI Approved :: GNU Affero General Public License v3
